puffinflow/__init__.py
puffinflow/version.py
puffinflow/core/__init__.py
puffinflow/core/config.py
puffinflow/core/agent/__init__.py
puffinflow/core/agent/base.py
puffinflow/core/agent/checkpoint.py
puffinflow/core/agent/context.py
puffinflow/core/agent/dependencies.py
puffinflow/core/agent/state.py
puffinflow/core/agent/decorators/__init__.py
puffinflow/core/agent/decorators/builder.py
puffinflow/core/agent/decorators/flexible.py
puffinflow/core/agent/decorators/inspection.py
puffinflow/core/agent/scheduling/__init__.py
puffinflow/core/agent/scheduling/builder.py
puffinflow/core/agent/scheduling/exceptions.py
puffinflow/core/agent/scheduling/inputs.py
puffinflow/core/agent/scheduling/parser.py
puffinflow/core/agent/scheduling/scheduler.py
puffinflow/core/coordination/__init__.py
puffinflow/core/coordination/agent_group.py
puffinflow/core/coordination/agent_pool.py
puffinflow/core/coordination/agent_team.py
puffinflow/core/coordination/coordinator.py
puffinflow/core/coordination/deadlock.py
puffinflow/core/coordination/fluent_api.py
puffinflow/core/coordination/primitives.py
puffinflow/core/coordination/rate_limiter.py
puffinflow/core/observability/__init__.py
puffinflow/core/observability/agent.py
puffinflow/core/observability/alerting.py
puffinflow/core/observability/config.py
puffinflow/core/observability/context.py
puffinflow/core/observability/core.py
puffinflow/core/observability/decorators.py
puffinflow/core/observability/events.py
puffinflow/core/observability/interfaces.py
puffinflow/core/observability/metrics.py
puffinflow/core/observability/tracing.py
puffinflow/core/reliability/__init__.py
puffinflow/core/reliability/bulkhead.py
puffinflow/core/reliability/circuit_breaker.py
puffinflow/core/reliability/leak_detector.py
puffinflow/core/resources/__init__.py
puffinflow/core/resources/allocation.py
puffinflow/core/resources/pool.py
puffinflow/core/resources/quotas.py
puffinflow/core/resources/requirements.py
puffinflow-2.0.1.dev0.dist-info/licenses/LICENSE
puffinflow-2.0.1.dev0.dist-info/METADATA
puffinflow-2.0.1.dev0.dist-info/WHEEL
puffinflow-2.0.1.dev0.dist-info/entry_points.txt
puffinflow-2.0.1.dev0.dist-info/top_level.txt
puffinflow-2.0.1.dev0.dist-info/RECORD
