Metadata-Version: 2.4
Name: puffinflow
Version: 2.0.1.dev0
Summary: A powerful Python workflow orchestration framework with advanced resource management and observability
Author-email: Mohamed Ahmed <mohamed.ahmed.4894@gmail.com>
Maintainer-email: Mohamed Ahmed <mohamed.ahmed.4894@gmail.com>
License: MIT
Project-URL: Homepage, https://github.com/m-ahmed-elbeskeri/puffinflow-main
Project-URL: Documentation, https://puffinflow.readthedocs.io
Project-URL: Repository, https://github.com/m-ahmed-elbeskeri/puffinflow-main.git
Project-URL: Bug Tracker, https://github.com/m-ahmed-elbeskeri/puffinflow-main/issues
Project-URL: Changelog, https://github.com/m-ahmed-elbeskeri/puffinflow-main/blob/main/CHANGELOG.md
Project-URL: Funding, https://github.com/sponsors/m-ahmed-elbeskeri
Keywords: workflow,orchestration,async,state-management,resource-allocation,task-execution,distributed-systems,monitoring,observability,tracing,metrics,coordination
Classifier: Development Status :: 4 - Beta
Classifier: Intended Audience :: Developers
Classifier: License :: OSI Approved :: MIT License
Classifier: Operating System :: OS Independent
Classifier: Programming Language :: Python :: 3
Classifier: Programming Language :: Python :: 3.9
Classifier: Programming Language :: Python :: 3.10
Classifier: Programming Language :: Python :: 3.11
Classifier: Programming Language :: Python :: 3.12
Classifier: Programming Language :: Python :: 3.13
Classifier: Topic :: Software Development :: Libraries :: Python Modules
Classifier: Topic :: System :: Distributed Computing
Classifier: Topic :: System :: Monitoring
Classifier: Topic :: System :: Systems Administration
Classifier: Framework :: AsyncIO
Classifier: Typing :: Typed
Requires-Python: >=3.9
License-File: LICENSE
Requires-Dist: pydantic<3.0.0,>=2.0.0
Requires-Dist: pydantic-settings<3.0.0,>=2.0.0
Requires-Dist: structlog>=23.1.0
Requires-Dist: typing-extensions>=4.8.0; python_version < "3.11"
Requires-Dist: aiohttp>=3.9.0
Requires-Dist: prometheus-client>=0.19.0
Requires-Dist: psutil>=5.9.0
Provides-Extra: dev
Requires-Dist: pytest>=7.4.0; extra == "dev"
Requires-Dist: pytest-asyncio>=0.21.0; extra == "dev"
Requires-Dist: pytest-cov>=4.1.0; extra == "dev"
Requires-Dist: pytest-mock>=3.12.0; extra == "dev"
Requires-Dist: pytest-benchmark>=4.0.0; extra == "dev"
Requires-Dist: pytest-timeout>=2.2.0; extra == "dev"
Requires-Dist: pytest-xdist>=3.5.0; extra == "dev"
Requires-Dist: black>=23.12.0; extra == "dev"
Requires-Dist: ruff>=0.1.8; extra == "dev"
Requires-Dist: mypy>=1.8.0; extra == "dev"
Requires-Dist: types-psutil>=5.9.0; extra == "dev"
Requires-Dist: pre-commit>=3.6.0; extra == "dev"
Requires-Dist: tox>=4.11.0; extra == "dev"
Requires-Dist: coverage[toml]>=7.3.0; extra == "dev"
Provides-Extra: docs
Requires-Dist: sphinx>=7.1.0; extra == "docs"
Requires-Dist: sphinx-rtd-theme>=2.0.0; extra == "docs"
Requires-Dist: sphinx-autodoc-typehints>=1.25.0; extra == "docs"
Requires-Dist: myst-parser>=2.0.0; extra == "docs"
Requires-Dist: sphinxcontrib-asyncio>=0.3.0; extra == "docs"
Provides-Extra: cli
Requires-Dist: typer[all]>=0.9.0; extra == "cli"
Requires-Dist: rich>=13.7.0; extra == "cli"
Requires-Dist: click>=8.1.0; extra == "cli"
Provides-Extra: observability
Requires-Dist: prometheus-client>=0.19.0; extra == "observability"
Requires-Dist: psutil>=5.9.0; extra == "observability"
Requires-Dist: opentelemetry-api<2.0.0,>=1.23.0; extra == "observability"
Requires-Dist: opentelemetry-sdk<2.0.0,>=1.23.0; extra == "observability"
Requires-Dist: opentelemetry-exporter-otlp-proto-grpc<2.0.0,>=1.23.0; extra == "observability"
Requires-Dist: opentelemetry-exporter-jaeger-thrift<2.0.0,>=1.21.0; extra == "observability"
Requires-Dist: opentelemetry-instrumentation-asyncio<1.0.0,>=0.44b0; extra == "observability"
Requires-Dist: opentelemetry-instrumentation-logging<1.0.0,>=0.44b0; extra == "observability"
Requires-Dist: aiohttp>=3.9.0; extra == "observability"
Requires-Dist: httpx>=0.26.0; extra == "observability"
Requires-Dist: aiosmtplib>=3.0.0; extra == "observability"
Requires-Dist: deprecated>=1.2.6; extra == "observability"
Provides-Extra: monitoring
Requires-Dist: prometheus-client>=0.19.0; extra == "monitoring"
Requires-Dist: opentelemetry-api<2.0.0,>=1.23.0; extra == "monitoring"
Requires-Dist: opentelemetry-sdk<2.0.0,>=1.23.0; extra == "monitoring"
Requires-Dist: opentelemetry-exporter-otlp-proto-grpc<2.0.0,>=1.23.0; extra == "monitoring"
Requires-Dist: opentelemetry-instrumentation-asyncio<1.0.0,>=0.44b0; extra == "monitoring"
Provides-Extra: integrations
Requires-Dist: fastapi>=0.108.0; extra == "integrations"
Requires-Dist: celery>=5.3.0; extra == "integrations"
Requires-Dist: kubernetes>=28.0.0; extra == "integrations"
Requires-Dist: redis>=5.0.0; extra == "integrations"
Requires-Dist: httpx>=0.26.0; extra == "integrations"
Requires-Dist: psutil>=5.9.0; extra == "integrations"
Provides-Extra: performance
Requires-Dist: pytest-benchmark>=4.0.0; extra == "performance"
Requires-Dist: memory-profiler>=0.61.0; extra == "performance"
Requires-Dist: line-profiler>=4.1.0; extra == "performance"
Requires-Dist: py-spy>=0.3.14; extra == "performance"
Provides-Extra: security
Requires-Dist: bandit>=1.7.5; extra == "security"
Requires-Dist: safety>=2.3.0; extra == "security"
Requires-Dist: semgrep>=1.45.0; extra == "security"
Provides-Extra: all
Requires-Dist: typer[all]>=0.9.0; extra == "all"
Requires-Dist: rich>=13.7.0; extra == "all"
Requires-Dist: click>=8.1.0; extra == "all"
Requires-Dist: prometheus-client>=0.19.0; extra == "all"
Requires-Dist: psutil>=5.9.0; extra == "all"
Requires-Dist: opentelemetry-api<2.0.0,>=1.23.0; extra == "all"
Requires-Dist: opentelemetry-sdk<2.0.0,>=1.23.0; extra == "all"
Requires-Dist: opentelemetry-exporter-otlp-proto-grpc<2.0.0,>=1.23.0; extra == "all"
Requires-Dist: opentelemetry-exporter-jaeger-thrift<2.0.0,>=1.21.0; extra == "all"
Requires-Dist: opentelemetry-instrumentation-asyncio<1.0.0,>=0.44b0; extra == "all"
Requires-Dist: opentelemetry-instrumentation-logging<1.0.0,>=0.44b0; extra == "all"
Requires-Dist: aiohttp>=3.9.0; extra == "all"
Requires-Dist: httpx>=0.26.0; extra == "all"
Requires-Dist: aiosmtplib>=3.0.0; extra == "all"
Requires-Dist: fastapi>=0.108.0; extra == "all"
Requires-Dist: celery>=5.3.0; extra == "all"
Requires-Dist: kubernetes>=28.0.0; extra == "all"
Requires-Dist: redis>=5.0.0; extra == "all"
Dynamic: license-file
